slum-0.1.1.dist-info/METADATA
slum-0.1.1.dist-info/WHEEL
slum/__init__.py
slum/slum.cpython-312-darwin.so
slum-0.1.1.dist-info/RECORD
