Metadata-Version: 2.4
Name: slum
Version: 0.1.1
Classifier: Development Status :: 4 - Beta
Classifier: Intended Audience :: Developers
Classifier: License :: OSI Approved :: Apache Software License
Classifier: Programming Language :: Python :: 3
Classifier: Programming Language :: Python :: 3.8
Classifier: Programming Language :: Python :: 3.9
Classifier: Programming Language :: Python :: 3.10
Classifier: Programming Language :: Python :: 3.11
Classifier: Programming Language :: Python :: 3.12
Classifier: Programming Language :: Rust
Summary: Fleet orchestrator for tenement servers
Keywords: tenement,fleet,orchestrator,multi-tenant
Home-Page: https://slum.dev
Author-email: Russell Romney <russellromney@gmail.com>
License: Apache-2.0
Requires-Python: >=3.8
Project-URL: Homepage, https://slum.dev
Project-URL: Repository, https://github.com/russellromney/slum
